[
    {
        "rank": 1,
        "name": "(주)요즘에",
        "url": "http://minishop.gmarket.co.kr/yozme",
        "ceo": "최경희",
        "tel": "02-1877-6776",
        "worktime": "10시~16시",
        "fax": "070-4149-7189",
        "email": "annckh@daum.net",
        "businessnum": "206-86-62796",
        "addr": "서울특별시 강남구 학동로 21길20, 1층 (논현동,JHAUS)"
    },
    {
        "rank": 2,
        "name": "(주)브리치",
        "url": "http://minishop.gmarket.co.kr/brich",
        "ceo": "이진욱",
        "tel": "010-3729-3673",
        "worktime": "14시~19시",
        "fax": "070-4060-8284",
        "email": "seeun0703@brich.co.kr",
        "businessnum": "217-81-46767",
        "addr": "서울 강남구 봉은사로18길 85, L1층 (역삼동, 아트리아빌딩)"
    },
    {
        "rank": 3,
        "name": "(주)니트빈",
        "url": "http://minishop.gmarket.co.kr/friday7",
        "ceo": "윤예원",
        "tel": "02-2294-0301",
        "worktime": "10시~15시",
        "fax": "02-2294-0302",
        "email": "090213@daum.net",
        "businessnum": "201-86-20199",
        "addr": "서울 성동구 고산자로 349 (마장동,창원빌딩2층)"
    },
    {
        "rank": 4,
        "name": "(주)더샵스토리",
        "url": "http://minishop.gmarket.co.kr/friendkbt1",
        "ceo": "김병태",
        "tel": "0216617717",
        "worktime": "10시~17시",
        "fax": "0505-115-3518",
        "email": "chicfoxljh@chicfox.co.kr",
        "businessnum": "129-86-13135",
        "addr": "서울 송파구 동남로 127 (가락동, 성화빌딩5층)"
    },
    {
        "rank": 5,
        "name": "(주)피앤에프컴퍼니",
        "url": "http://minishop.gmarket.co.kr/pipin19",
        "ceo": "박명남",
        "tel": "01043143416",
        "worktime": "09시~18시",
        "fax": "070-4015-7196",
        "email": "pippin19@naver.com",
        "businessnum": "206-86-43692",
        "addr": "서울 광진구 능동 247-6 3층"
    },
    {
        "rank": 6,
        "name": "주식회사투투",
        "url": "http://minishop.gmarket.co.kr/twotwo22",
        "ceo": "박수옥",
        "tel": "0323267536",
        "worktime": "09시~17시",
        "fax": "032-502-7872",
        "email": "gabba_kim@naver.com",
        "businessnum": "688-81-01206",
        "addr": "인천 부평구 일신로 69 (일신동)"
    },
    {
        "rank": 7,
        "name": "구아바",
        "url": "http://minishop.gmarket.co.kr/loosedeli",
        "ceo": "전재홍",
        "tel": "01094056636",
        "worktime": "010-9405-6636",
        "fax": "guaba_official@naver.com",
        "email": "",
        "businessnum": "서울 광진구 긴고랑로 66, 3층 (중곡동, 중곡동 43빌딩)",
        "addr": ""
    },
    {
        "rank": 8,
        "name": "주식회사지원알엔티(JIWONR&T)",
        "url": "http://minishop.gmarket.co.kr/cocoblanc1",
        "ceo": "박현정",
        "tel": "1522-5429",
        "worktime": "10시~15시",
        "fax": "02-1522-5429",
        "email": "noble_park@naver.com",
        "businessnum": "848-87-00441",
        "addr": "서울 강북구 도봉로 144,6층  (미아동)"
    },
    {
        "rank": 9,
        "name": "몽띠에34(MONTIER34)",
        "url": "http://minishop.gmarket.co.kr/chicloose",
        "ceo": "임재범",
        "tel": "01071362334",
        "worktime": "02-6954-3224",
        "fax": "cs01@montier34.co.kr",
        "email": "",
        "businessnum": "서울특별시 강남구 도산대로53길 39, 1동 104호 (신사동)",
        "addr": ""
    },
    {
        "rank": 10,
        "name": "수맘",
        "url": "http://minishop.gmarket.co.kr/sumom",
        "ceo": "황대연",
        "tel": "07088152600",
        "worktime": "02-976-7755",
        "fax": "daeyun79@naver.com",
        "email": "",
        "businessnum": "서울 노원구 공릉로46길 32, 101동1201호(공릉동,삼익아파트)",
        "addr": ""
    },
    {
        "rank": 11,
        "name": "주식회사달컴퍼니(DALcompany)",
        "url": "http://minishop.gmarket.co.kr/darllyshop",
        "ceo": "강호철",
        "tel": "18993986",
        "worktime": "10시~16시",
        "fax": "070-2297-8818",
        "email": "ever6451@naver.com",
        "businessnum": "201-86-23478",
        "addr": "서울특별시 성동구 왕십리로 410, 131동 501호(하왕십리동, 센트라스)"
    },
    {
        "rank": 12,
        "name": "(주)로드블링",
        "url": "http://minishop.gmarket.co.kr/roadbling",
        "ceo": "김현희",
        "tel": "01066943301",
        "worktime": "070-4015-8833",
        "fax": "zmzmmm@naver.com",
        "email": "",
        "businessnum": "서울특별시 광진구 긴고랑로 66, 1층(중곡동)",
        "addr": ""
    },
    {
        "rank": 13,
        "name": "주식회사온리스타일(ONLYSTYLE)",
        "url": "http://minishop.gmarket.co.kr/gaenso",
        "ceo": "박종현",
        "tel": "1600-5968",
        "worktime": "10시~18시",
        "fax": "032-522-6896",
        "email": "onlystyle00@naver.com",
        "businessnum": "730-88-00036",
        "addr": "경기도 부천시 부천로 270, 5층,6층,7층,8층,9층 (도당동)(도당동)"
    },
    {
        "rank": 14,
        "name": "주식회사핑크시슬리",
        "url": "http://minishop.gmarket.co.kr/pinksisly",
        "ceo": "이현희",
        "tel": "16447471",
        "worktime": "10시~17시",
        "fax": "02-822-6451",
        "email": "pinksisly01@naver.com",
        "businessnum": "108-86-10126",
        "addr": "서울 서초구 서초대로40길 91 (서초동, 동초빌딩)"
    },
    {
        "rank": 15,
        "name": "주식회사어바웃스타일",
        "url": "http://minishop.gmarket.co.kr/macys1",
        "ceo": "한신영",
        "tel": "01034517209",
        "worktime": "10시~15시",
        "fax": "032-873-1711",
        "email": "snscom08@gmail.com",
        "businessnum": "180-87-00404",
        "addr": "인천광역시 남구 학익소로61번길 21-11, 306호(학익동)"
    },
    {
        "rank": 16,
        "name": "니트모아",
        "url": "http://minishop.gmarket.co.kr/knitmoa",
        "ceo": "오지훈",
        "tel": "01093539268",
        "worktime": "10시~16시",
        "fax": "032-1234-1234",
        "email": "yjihun7@naver.com",
        "businessnum": "122-24-43488",
        "addr": "경기 성남시 수정구 수정로 58 , 501 (수진동,세일띠아모)"
    },
    {
        "rank": 17,
        "name": "쉬블림로브",
        "url": "http://minishop.gmarket.co.kr/SublimeRobe",
        "ceo": "이재현",
        "tel": "0260829176",
        "worktime": "02-6083-9176",
        "fax": "SublimeRobe@daum.net",
        "email": "",
        "businessnum": "서울특별시 동대문구 천호대로83길 10, 1층 101호 (장안동)",
        "addr": ""
    },
    {
        "rank": 18,
        "name": "(주)브리치",
        "url": "http://minishop.gmarket.co.kr/brich",
        "ceo": "이진욱",
        "tel": "010-3729-3673",
        "worktime": "14시~19시",
        "fax": "070-4060-8284",
        "email": "seeun0703@brich.co.kr",
        "businessnum": "217-81-46767",
        "addr": "서울 강남구 봉은사로18길 85, L1층 (역삼동, 아트리아빌딩)"
    },
    {
        "rank": 19,
        "name": "메르시래빗",
        "url": "http://minishop.gmarket.co.kr/daymuse",
        "ceo": "윤종훈",
        "tel": "07041950524",
        "worktime": "010-6816-9321",
        "fax": "mercirabbit@naver.com",
        "email": "",
        "businessnum": "서울특별시 강서구 방화대로41길 42, 202호(방화동)",
        "addr": ""
    },
    {
        "rank": 20,
        "name": "주식회사다온샵",
        "url": "http://minishop.gmarket.co.kr/daonshop7",
        "ceo": "한미리",
        "tel": "01026941455",
        "worktime": "10시~16시",
        "fax": "070-4142-1455",
        "email": "daonshop7@naver.com",
        "businessnum": "225-86-00020",
        "addr": "서울특별시 성북구 화랑로11길 26, 지하층 B115,B116호 (하월곡동, 월곡갑을명가)"
    },
    {
        "rank": 21,
        "name": "(주)애플클로젯",
        "url": "http://minishop.gmarket.co.kr/cherry7033",
        "ceo": "엄동관",
        "tel": "1661-3085",
        "worktime": "01시~05시",
        "fax": "02-3394-7153",
        "email": "cherryville0@naver.com",
        "businessnum": "206-86-68825",
        "addr": "서울 중구 퇴계로 461 (황학동,민족통일대통령빌딩14층)"
    },
    {
        "rank": 22,
        "name": "주식회사키루",
        "url": "http://minishop.gmarket.co.kr/sweetbunny1",
        "ceo": "송재용",
        "tel": "0222994286",
        "worktime": "09시~15시",
        "fax": "02-2299-4286",
        "email": "hide0203@naver.com",
        "businessnum": "206-86-54618",
        "addr": "서울 성동구 마장동 마장로 260, 302(마장동,동우빌딩)"
    },
    {
        "rank": 23,
        "name": "뷰티플러스",
        "url": "http://minishop.gmarket.co.kr/chenyongnan",
        "ceo": "CHENYONGNAN",
        "tel": "01091171518",
        "worktime": "09시~15시",
        "fax": "070-7543-0508",
        "email": "a91171518@gmail.com",
        "businessnum": "754-43-00195",
        "addr": "서울 구로구 구로동로42길 60-24,지층(구로동)"
    },
    {
        "rank": 24,
        "name": "주식회사 메이킹유",
        "url": "http://minishop.gmarket.co.kr/makingu1",
        "ceo": "송준엽",
        "tel": "01084411912",
        "worktime": "02-919-1912",
        "fax": "nomsjy76@nate.com",
        "email": "",
        "businessnum": "서울특별시 성북구 오패산로3길 38, 지하1층 (하월곡동, 고려빌딩)",
        "addr": ""
    },
    {
        "rank": 25,
        "name": "(주)와이앤제이21",
        "url": "http://minishop.gmarket.co.kr/canmart100",
        "ceo": "김영주",
        "tel": "15446770",
        "worktime": "10시~17시",
        "fax": "051-314-5551",
        "email": "yjjason@naver.com",
        "businessnum": "606-86-31187",
        "addr": "부산 사상구 광장로56번길 48-12(괘법동)"
    },
    {
        "rank": 26,
        "name": "주식회사이노블",
        "url": "http://minishop.gmarket.co.kr/ennoble",
        "ceo": "조동은",
        "tel": "07043044345",
        "worktime": "070-7716-3408",
        "fax": "ykha604@daum.net",
        "email": "",
        "businessnum": "서울특별시 광진구 천호대로 596, 3층 302호(능동)",
        "addr": ""
    },
    {
        "rank": 27,
        "name": "(주)엔라인",
        "url": "http://minishop.gmarket.co.kr/naning9",
        "ceo": "이정민",
        "tel": "0216448883",
        "worktime": "09시~15시",
        "fax": "032-875-1972",
        "email": "yuri89@nate.com",
        "businessnum": "131-86-09236",
        "addr": "서울 종로구 충신동 55-1 7층"
    },
    {
        "rank": 28,
        "name": "루나스타일",
        "url": "http://minishop.gmarket.co.kr/lunashop3",
        "ceo": "장선식",
        "tel": "07076234899",
        "worktime": "plaza10000@naver.com",
        "fax": "764-14-01041",
        "email": "",
        "businessnum": "",
        "addr": ""
    },
    {
        "rank": 29,
        "name": "주식회사올리비에홀딩스",
        "url": "http://minishop.gmarket.co.kr/Liberec",
        "ceo": "조영석",
        "tel": "01080219050",
        "worktime": "031-968-9060",
        "fax": "lovely3478@nate.com",
        "email": "",
        "businessnum": "서울특별시 마포구 월드컵북로 396, 12층 (상암동, 누리꿈스퀘어 비지니스타워)",
        "addr": ""
    },
    {
        "rank": 30,
        "name": "에이블포워드",
        "url": "http://minishop.gmarket.co.kr/ablefoward",
        "ceo": "전재홍",
        "tel": "01094056636",
        "worktime": "09시~15시",
        "fax": "02-979-8348",
        "email": "ableforward@naver.com",
        "businessnum": "217-81-42801",
        "addr": "서울특별시 노원구 공릉동  584-10 연세빌딩 504호"
    }
]